api_client/__init__.py
api_client/_base.py
api_client/async_client.py
api_client/py.typed
api_client/sync_client.py
api_client/utils/__init__.py
api_client/utils/logs.py
api_client/utils/parse.py
sdlv_api_client-1.1.1.dist-info/LICENCE
sdlv_api_client-1.1.1.dist-info/METADATA
sdlv_api_client-1.1.1.dist-info/WHEEL
sdlv_api_client-1.1.1.dist-info/top_level.txt
sdlv_api_client-1.1.1.dist-info/RECORD
