Metadata-Version: 2.1
Name: sdlv_api_client
Version: 1.1.1
Summary: API Client Base class
Author-email: Eriks Karls <git@72.lv>
Project-URL: Homepage, https://pypi.org/project/sdlv-api-client/
Project-URL: Bug Reports, https://git.72.lv/eriks/api_client/issues
Project-URL: Funding, https://donate.pypi.org
Project-URL: Source, https://git.72.lv/eriks/api_client
Keywords: api,client,api-client
Classifier: Development Status :: 5 - Production/Stable
Classifier: Intended Audience :: Developers
Classifier: Programming Language :: Python :: 3
Classifier: Programming Language :: Python :: 3.10
Classifier: Programming Language :: Python :: 3.11
Classifier: Programming Language :: Python :: 3.12
Classifier: Programming Language :: Python :: 3 :: Only
Classifier: License :: OSI Approved :: MIT License
Classifier: Operating System :: OS Independent
Requires-Python: ~=3.10
License-File: LICENCE
Requires-Dist: httpx[http2] ~=0.27.0
Requires-Dist: pydantic ~=2.6
